pyechelle/CCD.py
pyechelle/__init__.py
pyechelle/_kernels.py
pyechelle/benchmark.py
pyechelle/benchmark_results.json
pyechelle/efficiency.py
pyechelle/hdfbuilder.py
pyechelle/kernel_creation.py
pyechelle/kernel_templates/import_template.jinja
pyechelle/kernel_templates/kernel_template.jinja
pyechelle/kernel_templates/singlemode_transform.jinja
pyechelle/kernel_templates/slit_template.jinja
pyechelle/kernel_templates/transformation_template.jinja
pyechelle/model_viewer.py
pyechelle/models/available_models.txt
pyechelle/optics.py
pyechelle/randomgen.py
pyechelle/raytrace_cuda.py
pyechelle/raytracing.py
pyechelle/simulator.py
pyechelle/slit.py
pyechelle/sources.py
pyechelle/spectrograph.py
pyechelle/telescope.py
pyechelle-0.4.0.dist-info/WHEEL
pyechelle-0.4.0.dist-info/entry_points.txt
pyechelle-0.4.0.dist-info/METADATA
pyechelle-0.4.0.dist-info/RECORD
