Metadata-Version: 2.3
Name: pyechelle
Version: 0.4.0
Summary: A fast generic spectrum simulator
Author: Julian Stuermer
Author-email: Julian Stuermer <julian@stuermer.science>
License: MIT
Requires-Dist: h5py>=3.10.0,<4.0.0
Requires-Dist: parmap>=1.7.0,<2.0.0
Requires-Dist: plotly>=5.17.0,<7.0.0
Requires-Dist: joblib>=1.3.2,<2.0.0
Requires-Dist: matplotlib>=3.8.0,<4.0.0
Requires-Dist: synphot>=1.3.post0,<2.0.0
Requires-Dist: numba>=0.59,<1.0
Requires-Dist: zospy>=1.1.1,<2.0.0 ; python_full_version >= '3.9' and python_full_version < '3.12' and sys_platform == 'win32'
Requires-Dist: scipy>=1.12.0,<2.0.0
Requires-Dist: astropy>=5.3.4,<8.0.0
Requires-Dist: pandas>=2.2.0,<3.0.0
Requires-Dist: skycalc-ipy>=0.4.0,<1.0.0
Requires-Dist: jupyter>=1.0.0,<2.0.0
Requires-Dist: pytest>=7.4.4
Requires-Dist: asdcache>=0.2.0
Requires-Python: >=3.9, <3.14
Project-URL: documentation, https://stuermer.gitlab.io/pyechelle/
Project-URL: homepage, https://gitlab.com/Stuermer/pyechelle
Project-URL: repository, https://gitlab.com/Stuermer/pyechelle
